materialxjson/__init__.py
materialxjson/__main__.py
materialxjson/core.py
materialxjson/json2mtlx.py
materialxjson/mtlx2json.py
materialxjson/data/MaterialsVariantsShoe.gltf_converted.mtlx
materialxjson/data/MaterialsVariantsShoe.gltf_converted_mtlx.json
materialxjson/data/MaterialsVariantsShoe.gltf_converted_mtlx_json.mtlx
materialxjson/data/standard_surface_default.mtlx
materialxjson/data/standard_surface_default_mtlx.json
materialxjson/data/standard_surface_default_mtlx_json.mtlx
materialxjson-1.39.4.dist-info/LICENSE
materialxjson-1.39.4.dist-info/METADATA
materialxjson-1.39.4.dist-info/WHEEL
materialxjson-1.39.4.dist-info/entry_points.txt
materialxjson-1.39.4.dist-info/top_level.txt
materialxjson-1.39.4.dist-info/RECORD
