Metadata-Version: 2.1
Name: materialxjson
Version: 1.39.4
Summary: Utilities handling I/O of MaterialX in JSON format
Author-email: Bernard Kwok <kwokcb@gmail.com>
License: MIT License
Project-URL: Homepage, https://kwokcb.github.io/materialxjson/
Project-URL: Issues, https://github.com/kwokcb/materialxjson/issues
Project-URL: Source Code, https://github.com/kwokcb/materialxjson
Project-URL: Documentation, https://kwokcb.github.io/materialxjson/
Classifier: Intended Audience :: Developers
Classifier: Programming Language :: Python :: 3
Classifier: Operating System :: OS Independent
Classifier: Topic :: Software Development :: Libraries :: Python Modules
Requires-Python: >=3.8
License-File: LICENSE
Requires-Dist: materialx==1.39.4
